ofx_processor/__init__.py
ofx_processor/downloaders/__init__.py
ofx_processor/downloaders/lcl.py
ofx_processor/main.py
ofx_processor/processors/__init__.py
ofx_processor/processors/bpvf.py
ofx_processor/processors/ce.py
ofx_processor/processors/lcl.py
ofx_processor/processors/revolut.py
ofx_processor/senders/__init__.py
ofx_processor/senders/email.py
ofx_processor/senders/home_assistant.py
ofx_processor/senders/sms.py
ofx_processor/senders/telegram.py
ofx_processor/utils/__init__.py
ofx_processor/utils/base_ofx.py
ofx_processor/utils/base_processor.py
ofx_processor/utils/config.py
ofx_processor/utils/utils.py
ofx_processor/utils/ynab.py
ofx_processor-4.5.5.dist-info/LICENSE
ofx_processor-4.5.5.dist-info/METADATA
ofx_processor-4.5.5.dist-info/WHEEL
ofx_processor-4.5.5.dist-info/entry_points.txt
ofx_processor-4.5.5.dist-info/RECORD
