Metadata-Version: 2.1
Name: ofx-processor
Version: 4.5.5
Summary: Personal ofx processor
Home-page: https://git.augendre.info/gaugendre/ofx-processor
Keywords: ynab,finances,finance automation
Author: Gabriel Augendre
Author-email: gabriel@augendre.info
Requires-Python: >=3.10,<4
Classifier: Development Status :: 5 - Production/Stable
Classifier: Environment :: Console
Classifier: Intended Audience :: End Users/Desktop
Classifier: License :: OSI Approved :: The Unlicense (Unlicense)
Classifier: Natural Language :: English
Classifier: Operating System :: MacOS :: MacOS X
Classifier: Operating System :: Microsoft :: Windows
Classifier: Operating System :: Unix
Classifier: Programming Language :: Python :: 3
Classifier: Programming Language :: Python :: 3.10
Classifier: Programming Language :: Python :: 3.11
Classifier: Programming Language :: Python :: 3.12
Classifier: Programming Language :: Python :: 3.13
Classifier: Programming Language :: Python :: 3 :: Only
Classifier: Topic :: Utilities
Requires-Dist: click (>=8.0.3)
Requires-Dist: dateparser (>=1.1.0)
Requires-Dist: ofxtools (>=0.9.4)
Requires-Dist: python-telegram-bot (>=20.0a4)
Requires-Dist: requests (>=2.24.0)
Requires-Dist: selenium (>=4.0.0)
Project-URL: Repository, https://git.augendre.info/gaugendre/ofx-processor
